invocare/ssh/__init__.py
invocare/ssh/_version.py
invocare/ssh/client.py
invocare/ssh/hostkeys.py
invocare_ssh-0.3.0.dist-info/DESCRIPTION.rst
invocare_ssh-0.3.0.dist-info/METADATA
invocare_ssh-0.3.0.dist-info/RECORD
invocare_ssh-0.3.0.dist-info/WHEEL
invocare_ssh-0.3.0.dist-info/metadata.json
invocare_ssh-0.3.0.dist-info/top_level.txt
